{
  "topic_id": "complex_numbers",
  "topic_title": "Complex Numbers",
  "subject": "mathematics",
  "class_level": "S5",
  "lessons": [
    {
      "id": "s5_math_cx_l1",
      "title": "Introduction to Complex Numbers",
      "duration_minutes": 25,
      "xp_reward": 75,
      "content": [
        {
          "type": "text",
          "body": "Complex numbers extend the real number system to include solutions to equations like x²+1=0. Every complex number has the form a+bi where i=√(-1)."
        },
        {
          "type": "formula",
          "body": "i = √(-1),  i² = -1,  i³ = -i,  i⁴ = 1\nComplex number: z = a + bi\nReal part: Re(z) = a\nImaginary part: Im(z) = b\nModulus: |z| = √(a²+b²)\nConjugate: z* = a - bi"
        },
        {
          "type": "example",
          "title": "Arithmetic Example",
          "body": "If z₁ = 3+2i and z₂ = 1-4i:\nz₁+z₂ = 4-2i\nz₁·z₂ = 3-12i+2i-8i² = 3-10i+8 = 11-10i\n|z₁| = √(9+4) = √13"
        }
      ],
      "quiz": {
        "pass_score": 60,
        "questions": [
          {
            "id": "q1",
            "type": "multiple_choice",
            "question": "What is i²?",
            "options": [
              "1",
              "-1",
              "i",
              "-i"
            ],
            "answer": "-1",
            "explanation": "i = √(-1), so i² = -1 by definition"
          },
          {
            "id": "q2",
            "type": "multiple_choice",
            "question": "What is the modulus of z = 3+4i?",
            "options": [
              "7",
              "5",
              "1",
              "25"
            ],
            "answer": "5",
            "explanation": "|z| = √(3²+4²) = √(9+16) = √25 = 5"
          },
          {
            "id": "q3",
            "type": "multiple_choice",
            "question": "The conjugate of 2-3i is:",
            "options": [
              "2+3i",
              "-2+3i",
              "-2-3i",
              "3+2i"
            ],
            "answer": "2+3i",
            "explanation": "The conjugate changes the sign of the imaginary part"
          },
          {
            "id": "q4",
            "type": "multiple_choice",
            "question": "What is (1+i)²?",
            "options": [
              "2i",
              "1+2i",
              "2+2i",
              "-2"
            ],
            "answer": "2i",
            "explanation": "(1+i)² = 1+2i+i² = 1+2i-1 = 2i"
          },
          {
            "id": "q5",
            "type": "multiple_choice",
            "question": "The real part of z = 5-7i is:",
            "options": [
              "-7",
              "5",
              "7",
              "-5"
            ],
            "answer": "5",
            "explanation": "In a+bi, the real part is a. Here a=5"
          },
          {
            "id": "complex_numbers_l1_q6",
            "type": "multiple_choice",
            "question": "What does simplifying an expression mean?",
            "options": [
              "Reducing it to its simplest equivalent form",
              "Making it longer",
              "Adding more variables",
              "Changing the answer"
            ],
            "answer": "Reducing it to its simplest equivalent form",
            "explanation": "Simplification means rewriting an expression in its simplest equivalent form by collecting like terms and applying arithmetic."
          },
          {
            "id": "complex_numbers_l1_q8",
            "type": "multiple_choice",
            "question": "Which of these is an example of a variable?",
            "options": [
              "x in 3x + 2",
              "The number 5",
              "The + sign",
              "A fraction"
            ],
            "answer": "x in 3x + 2",
            "explanation": "A variable is a letter (like x, y, n) that represents an unknown or changing value."
          },
          {
            "id": "complex_numbers_l1_q10",
            "type": "multiple_choice",
            "question": "What is 2x + 3x simplified?",
            "options": [
              "5x",
              "6x",
              "5x²",
              "23x"
            ],
            "answer": "5x",
            "explanation": "Collect like terms: 2x + 3x = 5x (both terms have the same variable x)."
          },
          {
            "id": "complex_numbers_l1_q12",
            "type": "multiple_choice",
            "question": "Solve for x: x + 7 = 15",
            "options": [
              "x = 8",
              "x = 22",
              "x = 7",
              "x = 15"
            ],
            "answer": "x = 8",
            "explanation": "Subtract 7 from both sides: x = 15 - 7 = 8."
          },
          {
            "id": "complex_numbers_l1_q14",
            "type": "multiple_choice",
            "question": "What is the result of expanding 4(y - 3)?",
            "options": [
              "4y - 12",
              "4y - 3",
              "y - 12",
              "4y + 12"
            ],
            "answer": "4y - 12",
            "explanation": "Distribute: 4 × y - 4 × 3 = 4y - 12."
          },
          {
            "id": "complex_numbers_l1_q16",
            "type": "multiple_choice",
            "question": "Which operation reverses addition?",
            "options": [
              "Subtraction",
              "Multiplication",
              "Division",
              "Squaring"
            ],
            "answer": "Subtraction",
            "explanation": "Subtraction is the inverse (reverse) of addition."
          },
          {
            "id": "complex_numbers_l1_q18",
            "type": "multiple_choice",
            "question": "What is 3² equal to?",
            "options": [
              "9",
              "6",
              "8",
              "12"
            ],
            "answer": "9",
            "explanation": "3² = 3 × 3 = 9. The exponent 2 means multiply the base by itself."
          },
          {
            "id": "complex_numbers_l1_q20",
            "type": "multiple_choice",
            "question": "Factorise: 4x + 8",
            "options": [
              "4(x + 2)",
              "4x + 8",
              "2(2x + 8)",
              "8(x + 1)"
            ],
            "answer": "4(x + 2)",
            "explanation": "The HCF of 4x and 8 is 4. So 4x + 8 = 4(x + 2)."
          },
          {
            "id": "complex_numbers_l1_q22",
            "type": "multiple_choice",
            "question": "What is the y-intercept of y = 3x + 5?",
            "options": [
              "5",
              "3",
              "0",
              "8"
            ],
            "answer": "5",
            "explanation": "In y = mx + c, c is the y-intercept. Here c = 5."
          },
          {
            "id": "complex_numbers_l1_q24",
            "type": "multiple_choice",
            "question": "Solve: 3x = 18",
            "options": [
              "x = 6",
              "x = 15",
              "x = 21",
              "x = 54"
            ],
            "answer": "x = 6",
            "explanation": "Divide both sides by 3: x = 18 ÷ 3 = 6."
          },
          {
            "id": "complex_numbers_l1_q26",
            "type": "multiple_choice",
            "question": "What is the formula for the area of a rectangle?",
            "options": [
              "A = length × width",
              "A = ½ × base × height",
              "A = π r²",
              "A = side²"
            ],
            "answer": "A = length × width",
            "explanation": "Area of a rectangle = length × width."
          },
          {
            "id": "complex_numbers_l1_q28",
            "type": "multiple_choice",
            "question": "Which of these is NOT a like term with 3x²?",
            "options": [
              "5x²",
              "−2x²",
              "x²",
              "3x"
            ],
            "answer": "5x²",
            "explanation": "Like terms must have the same variable AND the same power. 3x has power 1, not 2, so it is not a like term with 3x²."
          },
          {
            "id": "complex_numbers_l1_q30",
            "type": "multiple_choice",
            "question": "What is the gradient/slope of a horizontal line?",
            "options": [
              "0",
              "1",
              "Undefined",
              "∞"
            ],
            "answer": "0",
            "explanation": "A horizontal line has no rise, so gradient = rise/run = 0/run = 0."
          },
          {
            "id": "complex_numbers_l1_q32",
            "type": "multiple_choice",
            "question": "If a = 4 and b = 3, find 2a + b.",
            "options": [
              "11",
              "14",
              "7",
              "10"
            ],
            "answer": "11",
            "explanation": "Substitute: 2(4) + 3 = 8 + 3 = 11."
          },
          {
            "id": "complex_numbers_l1_q34",
            "type": "multiple_choice",
            "question": "What does the inequality x > 5 mean?",
            "options": [
              "x is greater than 5",
              "x is less than 5",
              "x equals 5",
              "x is at least 5"
            ],
            "answer": "x is greater than 5",
            "explanation": "The > symbol means 'greater than'. x > 5 means x takes values greater than (but not equal to) 5."
          }
        ]
      }
    },
    {
      "id": "s5_math_cn_l2",
      "title": "Argand Diagram and Modulus-Argument Form",
      "duration_minutes": 30,
      "xp_reward": 70,
      "content": [
        {
          "type": "formula",
          "body": "A complex number z = a + bi can be shown on an Argand diagram:\n• Real part (a) on x-axis\n• Imaginary part (b) on y-axis\n\nModulus: |z| = √(a² + b²)\nArgument: arg(z) = tan⁻¹(b/a) — angle from positive real axis\n\nPolar form: z = r(cosθ + i sinθ) = r∠θ"
        },
        {
          "type": "example",
          "title": "Converting Forms",
          "body": "z = 3 + 4i\n|z| = √(9+16) = 5\narg(z) = tan⁻¹(4/3) = 53.1°\nPolar: z = 5(cos53.1° + i sin53.1°)"
        },
        {
          "type": "formula",
          "body": "Multiplication in polar form:\nz₁z₂ = r₁r₂ ∠(θ₁+θ₂)\nMultiply moduli, ADD arguments\n\nDivision:\nz₁/z₂ = (r₁/r₂) ∠(θ₁−θ₂)\nDivide moduli, SUBTRACT arguments"
        }
      ],
      "quiz": {
        "pass_score": 60,
        "questions": [
          {
            "id": "q1",
            "type": "multiple_choice",
            "question": "What is the modulus of z = 3 + 4i?",
            "options": [
              "3",
              "4",
              "5",
              "7"
            ],
            "answer": "5",
            "explanation": "Modulus = √(3²+4²) = √(9+16) = √25 = 5"
          },
          {
            "id": "q2",
            "type": "multiple_choice",
            "question": "On an Argand diagram, the imaginary part is plotted on...",
            "options": [
              "x-axis",
              "y-axis",
              "Both axes",
              "The origin"
            ],
            "answer": "y-axis",
            "explanation": "The real part is on the x-axis and imaginary part on the y-axis of an Argand diagram."
          },
          {
            "id": "q3",
            "type": "multiple_choice",
            "question": "What is |3 − 4i|?",
            "options": [
              "−5",
              "1",
              "7",
              "5"
            ],
            "answer": "5",
            "explanation": "Modulus = √(3²+(−4)²) = √(9+16) = 5. Modulus is always positive."
          },
          {
            "id": "q4",
            "type": "multiple_choice",
            "question": "arg(1 + i) = ",
            "options": [
              "30°",
              "45°",
              "60°",
              "90°"
            ],
            "answer": "45°",
            "explanation": "arg = tan⁻¹(1/1) = 45°. Both parts equal, so angle is 45°."
          },
          {
            "id": "q5",
            "type": "multiple_choice",
            "question": "z₁ = 2∠30°, z₂ = 3∠40°. z₁z₂ = ",
            "options": [
              "6∠70°",
              "5∠70°",
              "6∠10°",
              "5∠1200°"
            ],
            "answer": "6∠70°",
            "explanation": "Multiply moduli: 2×3=6. Add arguments: 30°+40°=70°."
          },
          {
            "id": "q6",
            "type": "multiple_choice",
            "question": "The conjugate of z = 5 + 2i is...",
            "options": [
              "5 − 2i",
              "−5 + 2i",
              "−5 − 2i",
              "2 + 5i"
            ],
            "answer": "5 − 2i",
            "explanation": "The conjugate z* is formed by changing the sign of the imaginary part."
          },
          {
            "id": "q7",
            "type": "multiple_choice",
            "question": "z × z* for z = a + bi equals...",
            "options": [
              "a² + b²",
              "2a",
              "a² − b²",
              "2bi"
            ],
            "answer": "a² + b²",
            "explanation": "z × z* = (a+bi)(a−bi) = a² − b²i² = a² + b² = |z|²"
          },
          {
            "id": "q8",
            "type": "multiple_choice",
            "question": "In polar form r(cosθ + i sinθ), r is the...",
            "options": [
              "argument",
              "imaginary part",
              "modulus",
              "real part"
            ],
            "answer": "modulus",
            "explanation": "r is the modulus (distance from origin). θ is the argument (angle from positive real axis)."
          },
          {
            "id": "q9",
            "type": "multiple_choice",
            "question": "z₁ = 6∠80°, z₂ = 2∠30°. z₁/z₂ = ",
            "options": [
              "3∠50°",
              "4∠50°",
              "3∠110°",
              "12∠50°"
            ],
            "answer": "3∠50°",
            "explanation": "Divide moduli: 6/2=3. Subtract arguments: 80°−30°=50°."
          },
          {
            "id": "q10",
            "type": "multiple_choice",
            "question": "The point (0, −3) on an Argand diagram represents...",
            "options": [
              "−3",
              "3i",
              "−3i",
              "3"
            ],
            "answer": "−3i",
            "explanation": "The point (0,−3) has real part 0 and imaginary part −3, so it represents −3i."
          },
          {
            "id": "complex_numbers_l2_q11",
            "type": "multiple_choice",
            "question": "What does simplifying an expression mean?",
            "options": [
              "Reducing it to its simplest equivalent form",
              "Making it longer",
              "Adding more variables",
              "Changing the answer"
            ],
            "answer": "Reducing it to its simplest equivalent form",
            "explanation": "Simplification means rewriting an expression in its simplest equivalent form by collecting like terms and applying arithmetic."
          },
          {
            "id": "complex_numbers_l2_q13",
            "type": "multiple_choice",
            "question": "Which of these is an example of a variable?",
            "options": [
              "x in 3x + 2",
              "The number 5",
              "The + sign",
              "A fraction"
            ],
            "answer": "x in 3x + 2",
            "explanation": "A variable is a letter (like x, y, n) that represents an unknown or changing value."
          },
          {
            "id": "complex_numbers_l2_q15",
            "type": "multiple_choice",
            "question": "What is 2x + 3x simplified?",
            "options": [
              "5x",
              "6x",
              "5x²",
              "23x"
            ],
            "answer": "5x",
            "explanation": "Collect like terms: 2x + 3x = 5x (both terms have the same variable x)."
          },
          {
            "id": "complex_numbers_l2_q17",
            "type": "multiple_choice",
            "question": "Solve for x: x + 7 = 15",
            "options": [
              "x = 8",
              "x = 22",
              "x = 7",
              "x = 15"
            ],
            "answer": "x = 8",
            "explanation": "Subtract 7 from both sides: x = 15 - 7 = 8."
          },
          {
            "id": "complex_numbers_l2_q19",
            "type": "multiple_choice",
            "question": "What is the result of expanding 4(y - 3)?",
            "options": [
              "4y - 12",
              "4y - 3",
              "y - 12",
              "4y + 12"
            ],
            "answer": "4y - 12",
            "explanation": "Distribute: 4 × y - 4 × 3 = 4y - 12."
          },
          {
            "id": "complex_numbers_l2_q21",
            "type": "multiple_choice",
            "question": "Which operation reverses addition?",
            "options": [
              "Subtraction",
              "Multiplication",
              "Division",
              "Squaring"
            ],
            "answer": "Subtraction",
            "explanation": "Subtraction is the inverse (reverse) of addition."
          },
          {
            "id": "complex_numbers_l2_q23",
            "type": "multiple_choice",
            "question": "What is 3² equal to?",
            "options": [
              "9",
              "6",
              "8",
              "12"
            ],
            "answer": "9",
            "explanation": "3² = 3 × 3 = 9. The exponent 2 means multiply the base by itself."
          },
          {
            "id": "complex_numbers_l2_q25",
            "type": "multiple_choice",
            "question": "Factorise: 4x + 8",
            "options": [
              "4(x + 2)",
              "4x + 8",
              "2(2x + 8)",
              "8(x + 1)"
            ],
            "answer": "4(x + 2)",
            "explanation": "The HCF of 4x and 8 is 4. So 4x + 8 = 4(x + 2)."
          },
          {
            "id": "complex_numbers_l2_q27",
            "type": "multiple_choice",
            "question": "What is the y-intercept of y = 3x + 5?",
            "options": [
              "5",
              "3",
              "0",
              "8"
            ],
            "answer": "5",
            "explanation": "In y = mx + c, c is the y-intercept. Here c = 5."
          },
          {
            "id": "complex_numbers_l2_q29",
            "type": "multiple_choice",
            "question": "Solve: 3x = 18",
            "options": [
              "x = 6",
              "x = 15",
              "x = 21",
              "x = 54"
            ],
            "answer": "x = 6",
            "explanation": "Divide both sides by 3: x = 18 ÷ 3 = 6."
          }
        ]
      }
    },
    {
      "id": "s5_math_cn_l3",
      "title": "De Moivre's Theorem and Applications",
      "duration_minutes": 30,
      "xp_reward": 75,
      "content": [
        {
          "type": "formula",
          "body": "De Moivre's Theorem:\n[r(cosθ + i sinθ)]ⁿ = rⁿ(cos nθ + i sin nθ)\n\nFor unit modulus: (cosθ + i sinθ)ⁿ = cos nθ + i sin nθ\n\nEuler's formula: e^(iθ) = cosθ + i sinθ\nSo: e^(iπ) + 1 = 0 (Euler's identity)"
        },
        {
          "type": "example",
          "title": "Using De Moivre's Theorem",
          "body": "Find (1 + i)⁸\nFirst: |1+i| = √2, arg = 45°\nSo 1+i = √2 ∠ 45°\n(1+i)⁸ = (√2)⁸ ∠ (8×45°) = 16 ∠ 360° = 16(cos360° + i sin360°) = 16"
        },
        {
          "type": "example",
          "title": "nth Roots of Complex Numbers",
          "body": "Find cube roots of 8\n8 = 8∠0°\nCube roots: 2∠(0°/3) = 2∠0°, 2∠120°, 2∠240°\n= 2, 2∠120°, 2∠240°\n= 2, −1+i√3, −1−i√3"
        }
      ],
      "quiz": {
        "pass_score": 60,
        "questions": [
          {
            "id": "q1",
            "type": "multiple_choice",
            "question": "By De Moivre's theorem, (cosθ + i sinθ)⁵ = ",
            "options": [
              "cos5θ + i sin5θ",
              "5cosθ + 5i sinθ",
              "cos5θ − i sin5θ",
              "5(cosθ + i sinθ)"
            ],
            "answer": "cos5θ + i sin5θ",
            "explanation": "De Moivre: (cosθ+i sinθ)ⁿ = cos nθ + i sin nθ. With n=5: cos5θ + i sin5θ"
          },
          {
            "id": "q2",
            "type": "multiple_choice",
            "question": "Euler's identity states that e^(iπ) + 1 = ",
            "options": [
              "0",
              "2",
              "i",
              "π"
            ],
            "answer": "0",
            "explanation": "Euler's famous identity: e^(iπ) + 1 = 0, connecting e, i, π, 1, and 0."
          },
          {
            "id": "q3",
            "type": "multiple_choice",
            "question": "Find (√2 ∠45°)⁴",
            "options": [
              "4∠180°",
              "8∠90°",
              "4∠90°",
              "2∠180°"
            ],
            "answer": "4∠180°",
            "explanation": "(√2)⁴=4, 45°×4=180°. So 4∠180° = 4(cos180°+i sin180°) = −4"
          },
          {
            "id": "q4",
            "type": "multiple_choice",
            "question": "How many nth roots does every complex number have?",
            "options": [
              "1",
              "2",
              "n",
              "infinite"
            ],
            "answer": "n",
            "explanation": "Every non-zero complex number has exactly n distinct nth roots, equally spaced around the Argand diagram."
          },
          {
            "id": "q5",
            "type": "multiple_choice",
            "question": "The cube roots of unity are 1 and...",
            "options": [
              "i and −i",
              "−1 and i",
              "e^(2πi/3) and e^(4πi/3)",
              "√3 and −√3"
            ],
            "answer": "e^(2πi/3) and e^(4πi/3)",
            "explanation": "The cube roots of unity are 1, ω=e^(2πi/3), ω²=e^(4πi/3) where ω³=1."
          },
          {
            "id": "q6",
            "type": "multiple_choice",
            "question": "e^(iθ) = ",
            "options": [
              "cosθ + i sinθ",
              "cosθ − i sinθ",
              "i(cosθ+sinθ)",
              "eθ"
            ],
            "answer": "cosθ + i sinθ",
            "explanation": "Euler's formula: e^(iθ) = cosθ + i sinθ"
          },
          {
            "id": "q7",
            "type": "multiple_choice",
            "question": "What is (2∠30°)³?",
            "options": [
              "6∠90°",
              "8∠90°",
              "6∠30°",
              "8∠30°"
            ],
            "answer": "8∠90°",
            "explanation": "2³=8, 30°×3=90°. Answer: 8∠90°"
          },
          {
            "id": "q8",
            "type": "multiple_choice",
            "question": "The nth roots of a complex number are spaced how apart on the Argand diagram?",
            "options": [
              "360°/n",
              "90°/n",
              "180°/n",
              "360°×n"
            ],
            "answer": "360°/n",
            "explanation": "The n roots are equally spaced around a circle, each separated by 360°/n."
          },
          {
            "id": "q9",
            "type": "multiple_choice",
            "question": "Using De Moivre, cos3θ can be expressed as...",
            "options": [
              "3cosθ",
              "cos³θ−3cosθsin²θ",
              "3cos³θ",
              "cosθ−sinθ"
            ],
            "answer": "cos³θ−3cosθsin²θ",
            "explanation": "Expanding (cosθ+i sinθ)³ and taking real part gives cos3θ = cos³θ−3cosθsin²θ"
          },
          {
            "id": "q10",
            "type": "multiple_choice",
            "question": "The modulus of e^(iθ) is...",
            "options": [
              "θ",
              "0",
              "1",
              "e"
            ],
            "answer": "1",
            "explanation": "By Euler's formula, e^(iθ)=cosθ+i sinθ, and |cosθ+i sinθ|=√(cos²θ+sin²θ)=1"
          },
          {
            "id": "complex_numbers_l3_q11",
            "type": "multiple_choice",
            "question": "What does simplifying an expression mean?",
            "options": [
              "Reducing it to its simplest equivalent form",
              "Making it longer",
              "Adding more variables",
              "Changing the answer"
            ],
            "answer": "Reducing it to its simplest equivalent form",
            "explanation": "Simplification means rewriting an expression in its simplest equivalent form by collecting like terms and applying arithmetic."
          },
          {
            "id": "complex_numbers_l3_q13",
            "type": "multiple_choice",
            "question": "Which of these is an example of a variable?",
            "options": [
              "x in 3x + 2",
              "The number 5",
              "The + sign",
              "A fraction"
            ],
            "answer": "x in 3x + 2",
            "explanation": "A variable is a letter (like x, y, n) that represents an unknown or changing value."
          },
          {
            "id": "complex_numbers_l3_q15",
            "type": "multiple_choice",
            "question": "What is 2x + 3x simplified?",
            "options": [
              "5x",
              "6x",
              "5x²",
              "23x"
            ],
            "answer": "5x",
            "explanation": "Collect like terms: 2x + 3x = 5x (both terms have the same variable x)."
          },
          {
            "id": "complex_numbers_l3_q17",
            "type": "multiple_choice",
            "question": "Solve for x: x + 7 = 15",
            "options": [
              "x = 8",
              "x = 22",
              "x = 7",
              "x = 15"
            ],
            "answer": "x = 8",
            "explanation": "Subtract 7 from both sides: x = 15 - 7 = 8."
          },
          {
            "id": "complex_numbers_l3_q19",
            "type": "multiple_choice",
            "question": "What is the result of expanding 4(y - 3)?",
            "options": [
              "4y - 12",
              "4y - 3",
              "y - 12",
              "4y + 12"
            ],
            "answer": "4y - 12",
            "explanation": "Distribute: 4 × y - 4 × 3 = 4y - 12."
          },
          {
            "id": "complex_numbers_l3_q21",
            "type": "multiple_choice",
            "question": "Which operation reverses addition?",
            "options": [
              "Subtraction",
              "Multiplication",
              "Division",
              "Squaring"
            ],
            "answer": "Subtraction",
            "explanation": "Subtraction is the inverse (reverse) of addition."
          },
          {
            "id": "complex_numbers_l3_q23",
            "type": "multiple_choice",
            "question": "What is 3² equal to?",
            "options": [
              "9",
              "6",
              "8",
              "12"
            ],
            "answer": "9",
            "explanation": "3² = 3 × 3 = 9. The exponent 2 means multiply the base by itself."
          },
          {
            "id": "complex_numbers_l3_q25",
            "type": "multiple_choice",
            "question": "Factorise: 4x + 8",
            "options": [
              "4(x + 2)",
              "4x + 8",
              "2(2x + 8)",
              "8(x + 1)"
            ],
            "answer": "4(x + 2)",
            "explanation": "The HCF of 4x and 8 is 4. So 4x + 8 = 4(x + 2)."
          },
          {
            "id": "complex_numbers_l3_q27",
            "type": "multiple_choice",
            "question": "What is the y-intercept of y = 3x + 5?",
            "options": [
              "5",
              "3",
              "0",
              "8"
            ],
            "answer": "5",
            "explanation": "In y = mx + c, c is the y-intercept. Here c = 5."
          },
          {
            "id": "complex_numbers_l3_q29",
            "type": "multiple_choice",
            "question": "Solve: 3x = 18",
            "options": [
              "x = 6",
              "x = 15",
              "x = 21",
              "x = 54"
            ],
            "answer": "x = 6",
            "explanation": "Divide both sides by 3: x = 18 ÷ 3 = 6."
          }
        ]
      }
    },
    {
      "id": "complex_numbers_l4",
      "title": "Complex Numbers — Advanced Part 4",
      "duration_minutes": 33,
      "xp_reward": 100,
      "content": [
        {
          "type": "text",
          "body": "In this lesson, we explore advanced aspects of Complex Numbers. Build on what you have already learned and apply your knowledge to more challenging problems."
        },
        {
          "type": "heading",
          "body": "Learning Objectives"
        },
        {
          "type": "text",
          "body": "By the end of this lesson you should be able to: (1) Apply Complex Numbers concepts to complex problems. (2) Use appropriate formulas and methods. (3) Interpret results in context. (4) Connect this topic to related areas of mathematics."
        },
        {
          "type": "heading",
          "body": "Core Theory"
        },
        {
          "type": "text",
          "body": "This section of Complex Numbers builds on foundational knowledge. In mathematics, advanced problem-solving requires not just knowing formulas but understanding when and how to apply them. Study each worked example carefully."
        },
        {
          "type": "example",
          "title": "Worked Example 4.1",
          "body": "Consider a more complex problem on Complex Numbers. Approach: (1) Read and understand the problem. (2) Identify all given information. (3) Determine which concepts apply. (4) Solve systematically, showing all steps. (5) Check your answer is reasonable."
        },
        {
          "type": "example",
          "title": "Worked Example 4.2",
          "body": "Another type of problem you may encounter: Questions may test your ability to combine multiple concepts within Complex Numbers. Practice identifying the type of problem and the appropriate method before attempting to solve."
        },
        {
          "type": "text",
          "body": "Common examination questions on Complex Numbers include: definitions and explanations, numerical calculations, diagram interpretation, and analysis of given data. Make sure you can handle all types."
        },
        {
          "type": "heading",
          "body": "Summary and Review"
        },
        {
          "type": "text",
          "body": "You have now covered all lessons in Complex Numbers. Review the key concepts from each lesson, practice past paper questions, and ensure you can apply your knowledge confidently. Good luck in your studies!"
        }
      ],
      "quiz": {
        "pass_score": 60,
        "questions": [
          {
            "id": "complex_numbers_l4_q1",
            "type": "multiple_choice",
            "question": "What does simplifying an expression mean?",
            "options": [
              "Reducing it to its simplest equivalent form",
              "Making it longer",
              "Adding more variables",
              "Changing the answer"
            ],
            "answer": "Reducing it to its simplest equivalent form",
            "explanation": "Simplification means rewriting an expression in its simplest equivalent form by collecting like terms and applying arithmetic."
          },
          {
            "id": "complex_numbers_l4_q2",
            "type": "multiple_choice",
            "question": "Which of these is an example of a variable?",
            "options": [
              "x in 3x + 2",
              "The number 5",
              "The + sign",
              "A fraction"
            ],
            "answer": "x in 3x + 2",
            "explanation": "A variable is a letter (like x, y, n) that represents an unknown or changing value."
          },
          {
            "id": "complex_numbers_l4_q3",
            "type": "multiple_choice",
            "question": "What is 2x + 3x simplified?",
            "options": [
              "5x",
              "6x",
              "5x²",
              "23x"
            ],
            "answer": "5x",
            "explanation": "Collect like terms: 2x + 3x = 5x (both terms have the same variable x)."
          },
          {
            "id": "complex_numbers_l4_q4",
            "type": "multiple_choice",
            "question": "Solve for x: x + 7 = 15",
            "options": [
              "x = 8",
              "x = 22",
              "x = 7",
              "x = 15"
            ],
            "answer": "x = 8",
            "explanation": "Subtract 7 from both sides: x = 15 - 7 = 8."
          },
          {
            "id": "complex_numbers_l4_q5",
            "type": "multiple_choice",
            "question": "What is the result of expanding 4(y - 3)?",
            "options": [
              "4y - 12",
              "4y - 3",
              "y - 12",
              "4y + 12"
            ],
            "answer": "4y - 12",
            "explanation": "Distribute: 4 × y - 4 × 3 = 4y - 12."
          },
          {
            "id": "complex_numbers_l4_q6",
            "type": "multiple_choice",
            "question": "Which operation reverses addition?",
            "options": [
              "Subtraction",
              "Multiplication",
              "Division",
              "Squaring"
            ],
            "answer": "Subtraction",
            "explanation": "Subtraction is the inverse (reverse) of addition."
          },
          {
            "id": "complex_numbers_l4_q7",
            "type": "multiple_choice",
            "question": "What is 3² equal to?",
            "options": [
              "9",
              "6",
              "8",
              "12"
            ],
            "answer": "9",
            "explanation": "3² = 3 × 3 = 9. The exponent 2 means multiply the base by itself."
          },
          {
            "id": "complex_numbers_l4_q8",
            "type": "multiple_choice",
            "question": "Factorise: 4x + 8",
            "options": [
              "4(x + 2)",
              "4x + 8",
              "2(2x + 8)",
              "8(x + 1)"
            ],
            "answer": "4(x + 2)",
            "explanation": "The HCF of 4x and 8 is 4. So 4x + 8 = 4(x + 2)."
          },
          {
            "id": "complex_numbers_l4_q9",
            "type": "multiple_choice",
            "question": "What is the y-intercept of y = 3x + 5?",
            "options": [
              "5",
              "3",
              "0",
              "8"
            ],
            "answer": "5",
            "explanation": "In y = mx + c, c is the y-intercept. Here c = 5."
          },
          {
            "id": "complex_numbers_l4_q10",
            "type": "multiple_choice",
            "question": "Solve: 3x = 18",
            "options": [
              "x = 6",
              "x = 15",
              "x = 21",
              "x = 54"
            ],
            "answer": "x = 6",
            "explanation": "Divide both sides by 3: x = 18 ÷ 3 = 6."
          },
          {
            "id": "complex_numbers_l4_q11",
            "type": "multiple_choice",
            "question": "What is the formula for the area of a rectangle?",
            "options": [
              "A = length × width",
              "A = ½ × base × height",
              "A = π r²",
              "A = side²"
            ],
            "answer": "A = length × width",
            "explanation": "Area of a rectangle = length × width."
          },
          {
            "id": "complex_numbers_l4_q12",
            "type": "multiple_choice",
            "question": "Which of these is NOT a like term with 3x²?",
            "options": [
              "5x²",
              "−2x²",
              "x²",
              "3x"
            ],
            "answer": "5x²",
            "explanation": "Like terms must have the same variable AND the same power. 3x has power 1, not 2, so it is not a like term with 3x²."
          },
          {
            "id": "complex_numbers_l4_q13",
            "type": "multiple_choice",
            "question": "What is the gradient/slope of a horizontal line?",
            "options": [
              "0",
              "1",
              "Undefined",
              "∞"
            ],
            "answer": "0",
            "explanation": "A horizontal line has no rise, so gradient = rise/run = 0/run = 0."
          },
          {
            "id": "complex_numbers_l4_q14",
            "type": "multiple_choice",
            "question": "If a = 4 and b = 3, find 2a + b.",
            "options": [
              "11",
              "14",
              "7",
              "10"
            ],
            "answer": "11",
            "explanation": "Substitute: 2(4) + 3 = 8 + 3 = 11."
          },
          {
            "id": "complex_numbers_l4_q15",
            "type": "multiple_choice",
            "question": "What does the inequality x > 5 mean?",
            "options": [
              "x is greater than 5",
              "x is less than 5",
              "x equals 5",
              "x is at least 5"
            ],
            "answer": "x is greater than 5",
            "explanation": "The > symbol means 'greater than'. x > 5 means x takes values greater than (but not equal to) 5."
          },
          {
            "id": "complex_numbers_l4_q16",
            "type": "multiple_choice",
            "question": "Solve: 2(x + 3) = 14",
            "options": [
              "x = 4",
              "x = 5",
              "x = 7",
              "x = 11"
            ],
            "answer": "x = 4",
            "explanation": "Expand: 2x + 6 = 14. Subtract 6: 2x = 8. Divide: x = 4."
          },
          {
            "id": "complex_numbers_l4_q17",
            "type": "multiple_choice",
            "question": "The HCF of 12 and 18 is:",
            "options": [
              "6",
              "2",
              "3",
              "36"
            ],
            "answer": "6",
            "explanation": "Factors of 12: 1,2,3,4,6,12. Factors of 18: 1,2,3,6,9,18. Highest common factor = 6."
          },
          {
            "id": "complex_numbers_l4_q18",
            "type": "multiple_choice",
            "question": "What is the LCM of 4 and 6?",
            "options": [
              "12",
              "24",
              "2",
              "10"
            ],
            "answer": "12",
            "explanation": "Multiples of 4: 4,8,12,... Multiples of 6: 6,12,... Lowest common multiple = 12."
          },
          {
            "id": "complex_numbers_l4_q19",
            "type": "multiple_choice",
            "question": "Which number is prime?",
            "options": [
              "7",
              "9",
              "15",
              "21"
            ],
            "answer": "7",
            "explanation": "A prime number has exactly two factors: 1 and itself. 7 is prime (factors: 1 and 7 only)."
          },
          {
            "id": "complex_numbers_l4_q20",
            "type": "multiple_choice",
            "question": "What is 0.5 as a fraction?",
            "options": [
              "½",
              "⅓",
              "¼",
              "⅕"
            ],
            "answer": "½",
            "explanation": "0.5 = 5/10 = 1/2. You can verify: 1 ÷ 2 = 0.5."
          }
        ]
      }
    },
    {
      "id": "complex_numbers_l5",
      "title": "Complex Numbers — Advanced Part 5",
      "duration_minutes": 35,
      "xp_reward": 110,
      "content": [
        {
          "type": "text",
          "body": "In this lesson, we explore advanced aspects of Complex Numbers. Build on what you have already learned and apply your knowledge to more challenging problems."
        },
        {
          "type": "heading",
          "body": "Learning Objectives"
        },
        {
          "type": "text",
          "body": "By the end of this lesson you should be able to: (1) Apply Complex Numbers concepts to complex problems. (2) Use appropriate formulas and methods. (3) Interpret results in context. (4) Connect this topic to related areas of mathematics."
        },
        {
          "type": "heading",
          "body": "Core Theory"
        },
        {
          "type": "text",
          "body": "This section of Complex Numbers builds on foundational knowledge. In mathematics, advanced problem-solving requires not just knowing formulas but understanding when and how to apply them. Study each worked example carefully."
        },
        {
          "type": "example",
          "title": "Worked Example 5.1",
          "body": "Consider a more complex problem on Complex Numbers. Approach: (1) Read and understand the problem. (2) Identify all given information. (3) Determine which concepts apply. (4) Solve systematically, showing all steps. (5) Check your answer is reasonable."
        },
        {
          "type": "example",
          "title": "Worked Example 5.2",
          "body": "Another type of problem you may encounter: Questions may test your ability to combine multiple concepts within Complex Numbers. Practice identifying the type of problem and the appropriate method before attempting to solve."
        },
        {
          "type": "text",
          "body": "Common examination questions on Complex Numbers include: definitions and explanations, numerical calculations, diagram interpretation, and analysis of given data. Make sure you can handle all types."
        },
        {
          "type": "heading",
          "body": "Summary and Review"
        },
        {
          "type": "text",
          "body": "You have now covered all lessons in Complex Numbers. Review the key concepts from each lesson, practice past paper questions, and ensure you can apply your knowledge confidently. Good luck in your studies!"
        }
      ],
      "quiz": {
        "pass_score": 60,
        "questions": [
          {
            "id": "complex_numbers_l5_q1",
            "type": "multiple_choice",
            "question": "What does simplifying an expression mean?",
            "options": [
              "Reducing it to its simplest equivalent form",
              "Making it longer",
              "Adding more variables",
              "Changing the answer"
            ],
            "answer": "Reducing it to its simplest equivalent form",
            "explanation": "Simplification means rewriting an expression in its simplest equivalent form by collecting like terms and applying arithmetic."
          },
          {
            "id": "complex_numbers_l5_q2",
            "type": "multiple_choice",
            "question": "Which of these is an example of a variable?",
            "options": [
              "x in 3x + 2",
              "The number 5",
              "The + sign",
              "A fraction"
            ],
            "answer": "x in 3x + 2",
            "explanation": "A variable is a letter (like x, y, n) that represents an unknown or changing value."
          },
          {
            "id": "complex_numbers_l5_q3",
            "type": "multiple_choice",
            "question": "What is 2x + 3x simplified?",
            "options": [
              "5x",
              "6x",
              "5x²",
              "23x"
            ],
            "answer": "5x",
            "explanation": "Collect like terms: 2x + 3x = 5x (both terms have the same variable x)."
          },
          {
            "id": "complex_numbers_l5_q4",
            "type": "multiple_choice",
            "question": "Solve for x: x + 7 = 15",
            "options": [
              "x = 8",
              "x = 22",
              "x = 7",
              "x = 15"
            ],
            "answer": "x = 8",
            "explanation": "Subtract 7 from both sides: x = 15 - 7 = 8."
          },
          {
            "id": "complex_numbers_l5_q5",
            "type": "multiple_choice",
            "question": "What is the result of expanding 4(y - 3)?",
            "options": [
              "4y - 12",
              "4y - 3",
              "y - 12",
              "4y + 12"
            ],
            "answer": "4y - 12",
            "explanation": "Distribute: 4 × y - 4 × 3 = 4y - 12."
          },
          {
            "id": "complex_numbers_l5_q6",
            "type": "multiple_choice",
            "question": "Which operation reverses addition?",
            "options": [
              "Subtraction",
              "Multiplication",
              "Division",
              "Squaring"
            ],
            "answer": "Subtraction",
            "explanation": "Subtraction is the inverse (reverse) of addition."
          },
          {
            "id": "complex_numbers_l5_q7",
            "type": "multiple_choice",
            "question": "What is 3² equal to?",
            "options": [
              "9",
              "6",
              "8",
              "12"
            ],
            "answer": "9",
            "explanation": "3² = 3 × 3 = 9. The exponent 2 means multiply the base by itself."
          },
          {
            "id": "complex_numbers_l5_q8",
            "type": "multiple_choice",
            "question": "Factorise: 4x + 8",
            "options": [
              "4(x + 2)",
              "4x + 8",
              "2(2x + 8)",
              "8(x + 1)"
            ],
            "answer": "4(x + 2)",
            "explanation": "The HCF of 4x and 8 is 4. So 4x + 8 = 4(x + 2)."
          },
          {
            "id": "complex_numbers_l5_q9",
            "type": "multiple_choice",
            "question": "What is the y-intercept of y = 3x + 5?",
            "options": [
              "5",
              "3",
              "0",
              "8"
            ],
            "answer": "5",
            "explanation": "In y = mx + c, c is the y-intercept. Here c = 5."
          },
          {
            "id": "complex_numbers_l5_q10",
            "type": "multiple_choice",
            "question": "Solve: 3x = 18",
            "options": [
              "x = 6",
              "x = 15",
              "x = 21",
              "x = 54"
            ],
            "answer": "x = 6",
            "explanation": "Divide both sides by 3: x = 18 ÷ 3 = 6."
          },
          {
            "id": "complex_numbers_l5_q11",
            "type": "multiple_choice",
            "question": "What is the formula for the area of a rectangle?",
            "options": [
              "A = length × width",
              "A = ½ × base × height",
              "A = π r²",
              "A = side²"
            ],
            "answer": "A = length × width",
            "explanation": "Area of a rectangle = length × width."
          },
          {
            "id": "complex_numbers_l5_q12",
            "type": "multiple_choice",
            "question": "Which of these is NOT a like term with 3x²?",
            "options": [
              "5x²",
              "−2x²",
              "x²",
              "3x"
            ],
            "answer": "5x²",
            "explanation": "Like terms must have the same variable AND the same power. 3x has power 1, not 2, so it is not a like term with 3x²."
          },
          {
            "id": "complex_numbers_l5_q13",
            "type": "multiple_choice",
            "question": "What is the gradient/slope of a horizontal line?",
            "options": [
              "0",
              "1",
              "Undefined",
              "∞"
            ],
            "answer": "0",
            "explanation": "A horizontal line has no rise, so gradient = rise/run = 0/run = 0."
          },
          {
            "id": "complex_numbers_l5_q14",
            "type": "multiple_choice",
            "question": "If a = 4 and b = 3, find 2a + b.",
            "options": [
              "11",
              "14",
              "7",
              "10"
            ],
            "answer": "11",
            "explanation": "Substitute: 2(4) + 3 = 8 + 3 = 11."
          },
          {
            "id": "complex_numbers_l5_q15",
            "type": "multiple_choice",
            "question": "What does the inequality x > 5 mean?",
            "options": [
              "x is greater than 5",
              "x is less than 5",
              "x equals 5",
              "x is at least 5"
            ],
            "answer": "x is greater than 5",
            "explanation": "The > symbol means 'greater than'. x > 5 means x takes values greater than (but not equal to) 5."
          },
          {
            "id": "complex_numbers_l5_q16",
            "type": "multiple_choice",
            "question": "Solve: 2(x + 3) = 14",
            "options": [
              "x = 4",
              "x = 5",
              "x = 7",
              "x = 11"
            ],
            "answer": "x = 4",
            "explanation": "Expand: 2x + 6 = 14. Subtract 6: 2x = 8. Divide: x = 4."
          },
          {
            "id": "complex_numbers_l5_q17",
            "type": "multiple_choice",
            "question": "The HCF of 12 and 18 is:",
            "options": [
              "6",
              "2",
              "3",
              "36"
            ],
            "answer": "6",
            "explanation": "Factors of 12: 1,2,3,4,6,12. Factors of 18: 1,2,3,6,9,18. Highest common factor = 6."
          },
          {
            "id": "complex_numbers_l5_q18",
            "type": "multiple_choice",
            "question": "What is the LCM of 4 and 6?",
            "options": [
              "12",
              "24",
              "2",
              "10"
            ],
            "answer": "12",
            "explanation": "Multiples of 4: 4,8,12,... Multiples of 6: 6,12,... Lowest common multiple = 12."
          },
          {
            "id": "complex_numbers_l5_q19",
            "type": "multiple_choice",
            "question": "Which number is prime?",
            "options": [
              "7",
              "9",
              "15",
              "21"
            ],
            "answer": "7",
            "explanation": "A prime number has exactly two factors: 1 and itself. 7 is prime (factors: 1 and 7 only)."
          },
          {
            "id": "complex_numbers_l5_q20",
            "type": "multiple_choice",
            "question": "What is 0.5 as a fraction?",
            "options": [
              "½",
              "⅓",
              "¼",
              "⅕"
            ],
            "answer": "½",
            "explanation": "0.5 = 5/10 = 1/2. You can verify: 1 ÷ 2 = 0.5."
          }
        ]
      }
    },
    {
      "id": "complex_numbers_l6",
      "title": "Complex Numbers — Advanced Part 6",
      "duration_minutes": 37,
      "xp_reward": 120,
      "content": [
        {
          "type": "text",
          "body": "In this lesson, we explore advanced aspects of Complex Numbers. Build on what you have already learned and apply your knowledge to more challenging problems."
        },
        {
          "type": "heading",
          "body": "Learning Objectives"
        },
        {
          "type": "text",
          "body": "By the end of this lesson you should be able to: (1) Apply Complex Numbers concepts to complex problems. (2) Use appropriate formulas and methods. (3) Interpret results in context. (4) Connect this topic to related areas of mathematics."
        },
        {
          "type": "heading",
          "body": "Core Theory"
        },
        {
          "type": "text",
          "body": "This section of Complex Numbers builds on foundational knowledge. In mathematics, advanced problem-solving requires not just knowing formulas but understanding when and how to apply them. Study each worked example carefully."
        },
        {
          "type": "example",
          "title": "Worked Example 6.1",
          "body": "Consider a more complex problem on Complex Numbers. Approach: (1) Read and understand the problem. (2) Identify all given information. (3) Determine which concepts apply. (4) Solve systematically, showing all steps. (5) Check your answer is reasonable."
        },
        {
          "type": "example",
          "title": "Worked Example 6.2",
          "body": "Another type of problem you may encounter: Questions may test your ability to combine multiple concepts within Complex Numbers. Practice identifying the type of problem and the appropriate method before attempting to solve."
        },
        {
          "type": "text",
          "body": "Common examination questions on Complex Numbers include: definitions and explanations, numerical calculations, diagram interpretation, and analysis of given data. Make sure you can handle all types."
        },
        {
          "type": "heading",
          "body": "Summary and Review"
        },
        {
          "type": "text",
          "body": "You have now covered all lessons in Complex Numbers. Review the key concepts from each lesson, practice past paper questions, and ensure you can apply your knowledge confidently. Good luck in your studies!"
        }
      ],
      "quiz": {
        "pass_score": 60,
        "questions": [
          {
            "id": "complex_numbers_l6_q1",
            "type": "multiple_choice",
            "question": "What does simplifying an expression mean?",
            "options": [
              "Reducing it to its simplest equivalent form",
              "Making it longer",
              "Adding more variables",
              "Changing the answer"
            ],
            "answer": "Reducing it to its simplest equivalent form",
            "explanation": "Simplification means rewriting an expression in its simplest equivalent form by collecting like terms and applying arithmetic."
          },
          {
            "id": "complex_numbers_l6_q2",
            "type": "multiple_choice",
            "question": "Which of these is an example of a variable?",
            "options": [
              "x in 3x + 2",
              "The number 5",
              "The + sign",
              "A fraction"
            ],
            "answer": "x in 3x + 2",
            "explanation": "A variable is a letter (like x, y, n) that represents an unknown or changing value."
          },
          {
            "id": "complex_numbers_l6_q3",
            "type": "multiple_choice",
            "question": "What is 2x + 3x simplified?",
            "options": [
              "5x",
              "6x",
              "5x²",
              "23x"
            ],
            "answer": "5x",
            "explanation": "Collect like terms: 2x + 3x = 5x (both terms have the same variable x)."
          },
          {
            "id": "complex_numbers_l6_q4",
            "type": "multiple_choice",
            "question": "Solve for x: x + 7 = 15",
            "options": [
              "x = 8",
              "x = 22",
              "x = 7",
              "x = 15"
            ],
            "answer": "x = 8",
            "explanation": "Subtract 7 from both sides: x = 15 - 7 = 8."
          },
          {
            "id": "complex_numbers_l6_q5",
            "type": "multiple_choice",
            "question": "What is the result of expanding 4(y - 3)?",
            "options": [
              "4y - 12",
              "4y - 3",
              "y - 12",
              "4y + 12"
            ],
            "answer": "4y - 12",
            "explanation": "Distribute: 4 × y - 4 × 3 = 4y - 12."
          },
          {
            "id": "complex_numbers_l6_q6",
            "type": "multiple_choice",
            "question": "Which operation reverses addition?",
            "options": [
              "Subtraction",
              "Multiplication",
              "Division",
              "Squaring"
            ],
            "answer": "Subtraction",
            "explanation": "Subtraction is the inverse (reverse) of addition."
          },
          {
            "id": "complex_numbers_l6_q7",
            "type": "multiple_choice",
            "question": "What is 3² equal to?",
            "options": [
              "9",
              "6",
              "8",
              "12"
            ],
            "answer": "9",
            "explanation": "3² = 3 × 3 = 9. The exponent 2 means multiply the base by itself."
          },
          {
            "id": "complex_numbers_l6_q8",
            "type": "multiple_choice",
            "question": "Factorise: 4x + 8",
            "options": [
              "4(x + 2)",
              "4x + 8",
              "2(2x + 8)",
              "8(x + 1)"
            ],
            "answer": "4(x + 2)",
            "explanation": "The HCF of 4x and 8 is 4. So 4x + 8 = 4(x + 2)."
          },
          {
            "id": "complex_numbers_l6_q9",
            "type": "multiple_choice",
            "question": "What is the y-intercept of y = 3x + 5?",
            "options": [
              "5",
              "3",
              "0",
              "8"
            ],
            "answer": "5",
            "explanation": "In y = mx + c, c is the y-intercept. Here c = 5."
          },
          {
            "id": "complex_numbers_l6_q10",
            "type": "multiple_choice",
            "question": "Solve: 3x = 18",
            "options": [
              "x = 6",
              "x = 15",
              "x = 21",
              "x = 54"
            ],
            "answer": "x = 6",
            "explanation": "Divide both sides by 3: x = 18 ÷ 3 = 6."
          },
          {
            "id": "complex_numbers_l6_q11",
            "type": "multiple_choice",
            "question": "What is the formula for the area of a rectangle?",
            "options": [
              "A = length × width",
              "A = ½ × base × height",
              "A = π r²",
              "A = side²"
            ],
            "answer": "A = length × width",
            "explanation": "Area of a rectangle = length × width."
          },
          {
            "id": "complex_numbers_l6_q12",
            "type": "multiple_choice",
            "question": "Which of these is NOT a like term with 3x²?",
            "options": [
              "5x²",
              "−2x²",
              "x²",
              "3x"
            ],
            "answer": "5x²",
            "explanation": "Like terms must have the same variable AND the same power. 3x has power 1, not 2, so it is not a like term with 3x²."
          },
          {
            "id": "complex_numbers_l6_q13",
            "type": "multiple_choice",
            "question": "What is the gradient/slope of a horizontal line?",
            "options": [
              "0",
              "1",
              "Undefined",
              "∞"
            ],
            "answer": "0",
            "explanation": "A horizontal line has no rise, so gradient = rise/run = 0/run = 0."
          },
          {
            "id": "complex_numbers_l6_q14",
            "type": "multiple_choice",
            "question": "If a = 4 and b = 3, find 2a + b.",
            "options": [
              "11",
              "14",
              "7",
              "10"
            ],
            "answer": "11",
            "explanation": "Substitute: 2(4) + 3 = 8 + 3 = 11."
          },
          {
            "id": "complex_numbers_l6_q15",
            "type": "multiple_choice",
            "question": "What does the inequality x > 5 mean?",
            "options": [
              "x is greater than 5",
              "x is less than 5",
              "x equals 5",
              "x is at least 5"
            ],
            "answer": "x is greater than 5",
            "explanation": "The > symbol means 'greater than'. x > 5 means x takes values greater than (but not equal to) 5."
          },
          {
            "id": "complex_numbers_l6_q16",
            "type": "multiple_choice",
            "question": "Solve: 2(x + 3) = 14",
            "options": [
              "x = 4",
              "x = 5",
              "x = 7",
              "x = 11"
            ],
            "answer": "x = 4",
            "explanation": "Expand: 2x + 6 = 14. Subtract 6: 2x = 8. Divide: x = 4."
          },
          {
            "id": "complex_numbers_l6_q17",
            "type": "multiple_choice",
            "question": "The HCF of 12 and 18 is:",
            "options": [
              "6",
              "2",
              "3",
              "36"
            ],
            "answer": "6",
            "explanation": "Factors of 12: 1,2,3,4,6,12. Factors of 18: 1,2,3,6,9,18. Highest common factor = 6."
          },
          {
            "id": "complex_numbers_l6_q18",
            "type": "multiple_choice",
            "question": "What is the LCM of 4 and 6?",
            "options": [
              "12",
              "24",
              "2",
              "10"
            ],
            "answer": "12",
            "explanation": "Multiples of 4: 4,8,12,... Multiples of 6: 6,12,... Lowest common multiple = 12."
          },
          {
            "id": "complex_numbers_l6_q19",
            "type": "multiple_choice",
            "question": "Which number is prime?",
            "options": [
              "7",
              "9",
              "15",
              "21"
            ],
            "answer": "7",
            "explanation": "A prime number has exactly two factors: 1 and itself. 7 is prime (factors: 1 and 7 only)."
          },
          {
            "id": "complex_numbers_l6_q20",
            "type": "multiple_choice",
            "question": "What is 0.5 as a fraction?",
            "options": [
              "½",
              "⅓",
              "¼",
              "⅕"
            ],
            "answer": "½",
            "explanation": "0.5 = 5/10 = 1/2. You can verify: 1 ÷ 2 = 0.5."
          }
        ]
      }
    }
  ]
}